pascal_voc_writer/__init__.py
pascal_voc_writer/templates/annotation.xml
pascal_voc_writer-0.1.4.dist-info/DESCRIPTION.rst
pascal_voc_writer-0.1.4.dist-info/METADATA
pascal_voc_writer-0.1.4.dist-info/RECORD
pascal_voc_writer-0.1.4.dist-info/WHEEL
pascal_voc_writer-0.1.4.dist-info/metadata.json
pascal_voc_writer-0.1.4.dist-info/top_level.txt
