Metadata-Version: 1.1
Name: pascal-voc-writer
Version: 0.1.4
Summary: Create image annotation XML files in the PASCAL VOC format
Home-page: https://github.com/AndrewCarterUK/pascal-voc-writer
Author: Andrew Carter
Author-email: andrewcarter1992@gmail.com
License: MIT
Keywords: pascal voc annotation writer xml
Platform: UNKNOWN
Classifier: Development Status :: 3 - Alpha
Classifier: Intended Audience :: Developers
Classifier: License :: OSI Approved :: MIT License
Classifier: Programming Language :: Python :: 2
Classifier: Programming Language :: Python :: 2.7
Classifier: Programming Language :: Python :: 3
Classifier: Programming Language :: Python :: 3.3
Classifier: Programming Language :: Python :: 3.4
Classifier: Programming Language :: Python :: 3.5
